Workbook

Sheet 📋 Trade Log
A1: 🚀 NQ FUTURES – TRADING JOURNAL
A2: Log your trades below — all statistics update automatically
A3: # | B3: Date | C3: Weekday | D3: Session | E3: Direction | F3: Entry | G3: Stop Loss | H3: Take Profit | I3: Exit | J3: Contracts | K3: Points (P/L) | L3: $ P/L | M3: R:R (Plan) | N3: R:R (Actual) | O3: Win/Loss | P3: Setup | Q3: Notes | R3: Mistake?
A4: =IF(B4<>"",ROW()-3,"") | C4: =IF(B4<>"",TEXT(B4,"DDDD"),"") | K4: =IF(AND(B4<>"",I4<>"",F4<>""),IF(E4="Long",(I4-F4)*20,(F4-I4)*20),"") | L4: =IF(AND(K4<>"",J4<>""),K4*J4,"") | M4: =IF(AND(F4<>"",G4<>"",H4<>""),IF(E4="Long",(H4-F4)/(F4-G4),(F4-H4)/(G4-F4)),"") | N4: =IF(AND(F4<>"",G4<>"",I4<>""),IF(E4="Long",(I4-F4)/(F4-G4),(F4-I4)/(G4-F4)),"") | O4: =IF(L4="","",IF(L4>0,"Win",IF(L4<0,"Loss","Break Even")))
A5: =IF(B5<>"",ROW()-3,"") | C5: =IF(B5<>"",TEXT(B5,"DDDD"),"") | K5: =IF(AND(B5<>"",I5<>"",F5<>""),IF(E5="Long",(I5-F5)*20,(F5-I5)*20),"") | L5: =IF(AND(K5<>"",J5<>""),K5*J5,"") | M5: =IF(AND(F5<>"",G5<>"",H5<>""),IF(E5="Long",(H5-F5)/(F5-G5),(F5-H5)/(G5-F5)),"") | N5: =IF(AND(F5<>"",G5<>"",I5<>""),IF(E5="Long",(I5-F5)/(F5-G5),(F5-I5)/(G5-F5)),"") | O5: =IF(L5="","",IF(L5>0,"Win",IF(L5<0,"Loss","Break Even")))
A6: =IF(B6<>"",ROW()-3,"") | C6: =IF(B6<>"",TEXT(B6,"DDDD"),"") | K6: =IF(AND(B6<>"",I6<>"",F6<>""),IF(E6="Long",(I6-F6)*20,(F6-I6)*20),"") | L6: =IF(AND(K6<>"",J6<>""),K6*J6,"") | M6: =IF(AND(F6<>"",G6<>"",H6<>""),IF(E6="Long",(H6-F6)/(F6-G6),(F6-H6)/(G6-F6)),"") | N6: =IF(AND(F6<>"",G6<>"",I6<>""),IF(E6="Long",(I6-F6)/(F6-G6),(F6-I6)/(G6-F6)),"") | O6: =IF(L6="","",IF(L6>0,"Win",IF(L6<0,"Loss","Break Even")))
A7: =IF(B7<>"",ROW()-3,"") | C7: =IF(B7<>"",TEXT(B7,"DDDD"),"") | K7: =IF(AND(B7<>"",I7<>"",F7<>""),IF(E7="Long",(I7-F7)*20,(F7-I7)*20),"") | L7: =IF(AND(K7<>"",J7<>""),K7*J7,"") | M7: =IF(AND(F7<>"",G7<>"",H7<>""),IF(E7="Long",(H7-F7)/(F7-G7),(F7-H7)/(G7-F7)),"") | N7: =IF(AND(F7<>"",G7<>"",I7<>""),IF(E7="Long",(I7-F7)/(F7-G7),(F7-I7)/(G7-F7)),"") | O7: =IF(L7="","",IF(L7>0,"Win",IF(L7<0,"Loss","Break Even")))
A8: =IF(B8<>"",ROW()-3,"") | C8: =IF(B8<>"",TEXT(B8,"DDDD"),"") | K8: =IF(AND(B8<>"",I8<>"",F8<>""),IF(E8="Long",(I8-F8)*20,(F8-I8)*20),"") | L8: =IF(AND(K8<>"",J8<>""),K8*J8,"") | M8: =IF(AND(F8<>"",G8<>"",H8<>""),IF(E8="Long",(H8-F8)/(F8-G8),(F8-H8)/(G8-F8)),"") | N8: =IF(AND(F8<>"",G8<>"",I8<>""),IF(E8="Long",(I8-F8)/(F8-G8),(F8-I8)/(G8-F8)),"") | O8: =IF(L8="","",IF(L8>0,"Win",IF(L8<0,"Loss","Break Even")))
A9: =IF(B9<>"",ROW()-3,"") | C9: =IF(B9<>"",TEXT(B9,"DDDD"),"") | K9: =IF(AND(B9<>"",I9<>"",F9<>""),IF(E9="Long",(I9-F9)*20,(F9-I9)*20),"") | L9: =IF(AND(K9<>"",J9<>""),K9*J9,"") | M9: =IF(AND(F9<>"",G9<>"",H9<>""),IF(E9="Long",(H9-F9)/(F9-G9),(F9-H9)/(G9-F9)),"") | N9: =IF(AND(F9<>"",G9<>"",I9<>""),IF(E9="Long",(I9-F9)/(F9-G9),(F9-I9)/(G9-F9)),"") | O9: =IF(L9="","",IF(L9>0,"Win",IF(L9<0,"Loss","Break Even")))
A10: =IF(B10<>"",ROW()-3,"") | C10: =IF(B10<>"",TEXT(B10,"DDDD"),"") | K10: =IF(AND(B10<>"",I10<>"",F10<>""),IF(E10="Long",(I10-F10)*20,(F10-I10)*20),"") | L10: =IF(AND(K10<>"",J10<>""),K10*J10,"") | M10: =IF(AND(F10<>"",G10<>"",H10<>""),IF(E10="Long",(H10-F10)/(F10-G10),(F10-H10)/(G10-F10)),"") | N10: =IF(AND(F10<>"",G10<>"",I10<>""),IF(E10="Long",(I10-F10)/(F10-G10),(F10-I10)/(G10-F10)),"") | O10: =IF(L10="","",IF(L10>0,"Win",IF(L10<0,"Loss","Break Even")))
A11: =IF(B11<>"",ROW()-3,"") | C11: =IF(B11<>"",TEXT(B11,"DDDD"),"") | K11: =IF(AND(B11<>"",I11<>"",F11<>""),IF(E11="Long",(I11-F11)*20,(F11-I11)*20),"") | L11: =IF(AND(K11<>"",J11<>""),K11*J11,"") | M11: =IF(AND(F11<>"",G11<>"",H11<>""),IF(E11="Long",(H11-F11)/(F11-G11),(F11-H11)/(G11-F11)),"") | N11: =IF(AND(F11<>"",G11<>"",I11<>""),IF(E11="Long",(I11-F11)/(F11-G11),(F11-I11)/(G11-F11)),"") | O11: =IF(L11="","",IF(L11>0,"Win",IF(L11<0,"Loss","Break Even")))
A12: =IF(B12<>"",ROW()-3,"") | C12: =IF(B12<>"",TEXT(B12,"DDDD"),"") | K12: =IF(AND(B12<>"",I12<>"",F12<>""),IF(E12="Long",(I12-F12)*20,(F12-I12)*20),"") | L12: =IF(AND(K12<>"",J12<>""),K12*J12,"") | M12: =IF(AND(F12<>"",G12<>"",H12<>""),IF(E12="Long",(H12-F12)/(F12-G12),(F12-H12)/(G12-F12)),"") | N12: =IF(AND(F12<>"",G12<>"",I12<>""),IF(E12="Long",(I12-F12)/(F12-G12),(F12-I12)/(G12-F12)),"") | O12: =IF(L12="","",IF(L12>0,"Win",IF(L12<0,"Loss","Break Even")))
A13: =IF(B13<>"",ROW()-3,"") | C13: =IF(B13<>"",TEXT(B13,"DDDD"),"") | K13: =IF(AND(B13<>"",I13<>"",F13<>""),IF(E13="Long",(I13-F13)*20,(F13-I13)*20),"") | L13: =IF(AND(K13<>"",J13<>""),K13*J13,"") | M13: =IF(AND(F13<>"",G13<>"",H13<>""),IF(E13="Long",(H13-F13)/(F13-G13),(F13-H13)/(G13-F13)),"") | N13: =IF(AND(F13<>"",G13<>"",I13<>""),IF(E13="Long",(I13-F13)/(F13-G13),(F13-I13)/(G13-F13)),"") | O13: =IF(L13="","",IF(L13>0,"Win",IF(L13<0,"Loss","Break Even")))
A14: =IF(B14<>"",ROW()-3,"") | C14: =IF(B14<>"",TEXT(B14,"DDDD"),"") | K14: =IF(AND(B14<>"",I14<>"",F14<>""),IF(E14="Long",(I14-F14)*20,(F14-I14)*20),"") | L14: =IF(AND(K14<>"",J14<>""),K14*J14,"") | M14: =IF(AND(F14<>"",G14<>"",H14<>""),IF(E14="Long",(H14-F14)/(F14-G14),(F14-H14)/(G14-F14)),"") | N14: =IF(AND(F14<>"",G14<>"",I14<>""),IF(E14="Long",(I14-F14)/(F14-G14),(F14-I14)/(G14-F14)),"") | O14: =IF(L14="","",IF(L14>0,"Win",IF(L14<0,"Loss","Break Even")))
A15: =IF(B15<>"",ROW()-3,"") | C15: =IF(B15<>"",TEXT(B15,"DDDD"),"") | K15: =IF(AND(B15<>"",I15<>"",F15<>""),IF(E15="Long",(I15-F15)*20,(F15-I15)*20),"") | L15: =IF(AND(K15<>"",J15<>""),K15*J15,"") | M15: =IF(AND(F15<>"",G15<>"",H15<>""),IF(E15="Long",(H15-F15)/(F15-G15),(F15-H15)/(G15-F15)),"") | N15: =IF(AND(F15<>"",G15<>"",I15<>""),IF(E15="Long",(I15-F15)/(F15-G15),(F15-I15)/(G15-F15)),"") | O15: =IF(L15="","",IF(L15>0,"Win",IF(L15<0,"Loss","Break Even")))
... A503: =IF(B503<>"",ROW()-3,"") | C503: =IF(B503<>"",TEXT(B503,"DDDD"),"") | K503: =IF(AND(B503<>"",I503<>"",F503<>""),IF(E503="Long",(I503-F503)*20,(F503-I503)*20),"") | L503: =IF(AND(K503<>"",J503<>""),K503*J503,"") | M503: =IF(AND(F503<>"",G503<>"",H503<>""),IF(E503="Long",(H503-F503)/(F503-G503),(F503-H503)/(G503-F503)),"") | N503: =IF(AND(F503<>"",G503<>"",I503<>""),IF(E503="Long",(I503-F503)/(F503-G503),(F503-I503)/(G503-F503)),"") | O503: =IF(L503="","",IF(L503>0,"Win",IF(L503<0,"Loss","Break Even")))

Sheet 📊 Statistics
A1: 📊 PERFORMANCE STATISTICS – NQ FUTURES
A3: 📈 GENERAL PERFORMANCE | D3: ⚡ RISK & REWARD
A4: Total Trades | B4: =COUNTA('📋 Trade Log'!O4:O503) -> 500 | D4: Avg R:R Plan | E4: =IFERROR(AVERAGE('📋 Trade Log'!M4:M503),0) -> 0
A5: Winners | B5: =COUNTIF('📋 Trade Log'!O4:O503,"Win") -> 0 | D5: Avg R:R Actual (W) | E5: =IFERROR(AVERAGEIF('📋 Trade Log'!O4:O503,"Win",'📋 Trade Log'!N4:N503),0) -> 0
A6: Losers | B6: =COUNTIF('📋 Trade Log'!O4:O503,"Loss") -> 0 | D6: Profit Factor | E6: =IFERROR(SUMIF('📋 Trade Log'!O4:O503,"Win",'📋 Trade Log'!L4:L503)/ABS(SUMIF('📋 Trade Log'!O4:O503,"Loss",'📋 Trade Log'!L4:L503)),0) -> 0
A7: Break Even | B7: =COUNTIF('📋 Trade Log'!O4:O503,"Break Even") -> 0 | D7: Expectancy ($) | E7: =IFERROR(B6*AVERAGEIF('📋 Trade Log'!O4:O503,"Win",'📋 Trade Log'!L4:L503)+B7*AVERAGEIF('📋 Trade Log'!O4:O503,"Loss",'📋 Trade Log'!L4:L503),0) -> 0
A8: Win Rate | B8: =IFERROR(COUNTIF('📋 Trade Log'!O4:O503,"Win")/COUNTA('📋 Trade Log'!O4:O503),0) -> 0 | D8: Max Drawdown ($) | E8: =IFERROR(MIN(minifs('📋 Trade Log'!L4:L503,'📋 Trade Log'!O4:O503,"Loss")),0) -> 0
A9: Loss Rate | B9: =IFERROR(COUNTIF('📋 Trade Log'!O4:O503,"Loss")/COUNTA('📋 Trade Log'!O4:O503),0) -> 0 | D9: Avg Points Win | E9: =IFERROR(AVERAGEIF('📋 Trade Log'!O4:O503,"Win",'📋 Trade Log'!K4:K503),0) -> 0
A10: Net P/L | B10: =IFERROR(SUM('📋 Trade Log'!L4:L503),0) -> 0 | D10: Avg Points Loss | E10: =IFERROR(AVERAGEIF('📋 Trade Log'!O4:O503,"Loss",'📋 Trade Log'!K4:K503),0) -> 0
A11: Avg Win / Trade | B11: =IFERROR(AVERAGEIF('📋 Trade Log'!O4:O503,"Win",'📋 Trade Log'!L4:L503),0) -> 0
A12: Avg Loss / Trade | B12: =IFERROR(AVERAGEIF('📋 Trade Log'!O4:O503,"Loss",'📋 Trade Log'!L4:L503),0) -> 0
A13: Best Trade | B13: =IFERROR(MAX('📋 Trade Log'!L4:L503),0) -> 0
A14: Worst Trade | B14: =IFERROR(MIN('📋 Trade Log'!L4:L503),0) -> 0
A17: 📅 DAY OF WEEK ANALYSIS
A18: Day | B18: Trades | C18: Wins | D18: Losses | E18: Win Rate | F18: Net P/L
A19: Monday | B19: =COUNTIF('📋 Trade Log'!C4:C503,A19) -> 0 | C19: =COUNTIFS('📋 Trade Log'!C4:C503,A19,'📋 Trade Log'!O4:O503,"Win") -> 0 | D19: =COUNTIFS('📋 Trade Log'!C4:C503,A19,'📋 Trade Log'!O4:O503,"Loss") -> 0 | E19: =IFERROR(C19/B19,0) -> 0 | F19: =IFERROR(SUMIF('📋 Trade Log'!C4:C503,A19,'📋 Trade Log'!L4:L503),0) -> 0
A20: Tuesday | B20: =COUNTIF('📋 Trade Log'!C4:C503,A20) -> 0 | C20: =COUNTIFS('📋 Trade Log'!C4:C503,A20,'📋 Trade Log'!O4:O503,"Win") -> 0 | D20: =COUNTIFS('📋 Trade Log'!C4:C503,A20,'📋 Trade Log'!O4:O503,"Loss") -> 0 | E20: =IFERROR(C20/B20,0) -> 0 | F20: =IFERROR(SUMIF('📋 Trade Log'!C4:C503,A20,'📋 Trade Log'!L4:L503),0) -> 0
A21: Wednesday | B21: =COUNTIF('📋 Trade Log'!C4:C503,A21) -> 0 | C21: =COUNTIFS('📋 Trade Log'!C4:C503,A21,'📋 Trade Log'!O4:O503,"Win") -> 0 | D21: =COUNTIFS('📋 Trade Log'!C4:C503,A21,'📋 Trade Log'!O4:O503,"Loss") -> 0 | E21: =IFERROR(C21/B21,0) -> 0 | F21: =IFERROR(SUMIF('📋 Trade Log'!C4:C503,A21,'📋 Trade Log'!L4:L503),0) -> 0
A22: Thursday | B22: =COUNTIF('📋 Trade Log'!C4:C503,A22) -> 0 | C22: =COUNTIFS('📋 Trade Log'!C4:C503,A22,'📋 Trade Log'!O4:O503,"Win") -> 0 | D22: =COUNTIFS('📋 Trade Log'!C4:C503,A22,'📋 Trade Log'!O4:O503,"Loss") -> 0 | E22: =IFERROR(C22/B22,0) -> 0 | F22: =IFERROR(SUMIF('📋 Trade Log'!C4:C503,A22,'📋 Trade Log'!L4:L503),0) -> 0
A23: Friday | B23: =COUNTIF('📋 Trade Log'!C4:C503,A23) -> 0 | C23: =COUNTIFS('📋 Trade Log'!C4:C503,A23,'📋 Trade Log'!O4:O503,"Win") -> 0 | D23: =COUNTIFS('📋 Trade Log'!C4:C503,A23,'📋 Trade Log'!O4:O503,"Loss") -> 0 | E23: =IFERROR(C23/B23,0) -> 0 | F23: =IFERROR(SUMIF('📋 Trade Log'!C4:C503,A23,'📋 Trade Log'!L4:L503),0) -> 0
A26: 🕐 SESSION ANALYSIS
A27: Session | B27: Trades | C27: Wins | D27: Win Rate | E27: Net P/L | F27: Avg P/L
A28: Asia | B28: =COUNTIF('📋 Trade Log'!D4:D503,A28) -> 0 | C28: =COUNTIFS('📋 Trade Log'!D4:D503,A28,'📋 Trade Log'!O4:O503,"Win") -> 0 | D28: =IFERROR(C28/B28,0) -> 0 | E28: =IFERROR(SUMIF('📋 Trade Log'!D4:D503,A28,'📋 Trade Log'!L4:L503),0) -> 0 | F28: =IFERROR(AVERAGEIF('📋 Trade Log'!D4:D503,A28,'📋 Trade Log'!L4:L503),0) -> 0
A29: London | B29: =COUNTIF('📋 Trade Log'!D4:D503,A29) -> 0 | C29: =COUNTIFS('📋 Trade Log'!D4:D503,A29,'📋 Trade Log'!O4:O503,"Win") -> 0 | D29: =IFERROR(C29/B29,0) -> 0 | E29: =IFERROR(SUMIF('📋 Trade Log'!D4:D503,A29,'📋 Trade Log'!L4:L503),0) -> 0 | F29: =IFERROR(AVERAGEIF('📋 Trade Log'!D4:D503,A29,'📋 Trade Log'!L4:L503),0) -> 0
A30: NY Open | B30: =COUNTIF('📋 Trade Log'!D4:D503,A30) -> 0 | C30: =COUNTIFS('📋 Trade Log'!D4:D503,A30,'📋 Trade Log'!O4:O503,"Win") -> 0 | D30: =IFERROR(C30/B30,0) -> 0 | E30: =IFERROR(SUMIF('📋 Trade Log'!D4:D503,A30,'📋 Trade Log'!L4:L503),0) -> 0 | F30: =IFERROR(AVERAGEIF('📋 Trade Log'!D4:D503,A30,'📋 Trade Log'!L4:L503),0) -> 0
A31: New York | B31: =COUNTIF('📋 Trade Log'!D4:D503,A31) -> 0 | C31: =COUNTIFS('📋 Trade Log'!D4:D503,A31,'📋 Trade Log'!O4:O503,"Win") -> 0 | D31: =IFERROR(C31/B31,0) -> 0 | E31: =IFERROR(SUMIF('📋 Trade Log'!D4:D503,A31,'📋 Trade Log'!L4:L503),0) -> 0 | F31: =IFERROR(AVERAGEIF('📋 Trade Log'!D4:D503,A31,'📋 Trade Log'!L4:L503),0) -> 0

Sheet 📅 Monthly Overview
A1: 📅 MONTHLY PERFORMANCE – NQ FUTURES
A3: Month | B3: Trades | C3: Wins | D3: Losses | E3: Win Rate | F3: Net P/L | G3: Avg P/L | H3: Cum. P/L
A4: January | B4: =SUMPRODUCT((ISNUMBER('📋 Trade Log'!B4:B503))*(MONTH('📋 Trade Log'!B4:B503)=1)*('📋 Trade Log'!O4:O503<>"")*(1)) -> 0 | C4: =SUMPRODUCT((MONTH('📋 Trade Log'!B4:B503)=1)*('📋 Trade Log'!O4:O503="Win")) -> 0 | D4: =SUMPRODUCT((MONTH('📋 Trade Log'!B4:B503)=1)*('📋 Trade Log'!O4:O503="Loss")) -> 0 | E4: =IFERROR(C4/B4,0) -> 0 | F4: =IFERROR(SUMPRODUCT((ISNUMBER('📋 Trade Log'!B4:B503))*(MONTH('📋 Trade Log'!B4:B503)=1)*IF(ISNUMBER('📋 Trade Log'!L4:L503),'📋 Trade Log'!L4:L503,0)),0) -> 0 | G4: =IFERROR(F4/B4,0) -> 0 | H4: =SUM($F$4:F4) -> 0
A5: February | B5: =SUMPRODUCT((ISNUMBER('📋 Trade Log'!B4:B503))*(MONTH('📋 Trade Log'!B4:B503)=2)*('📋 Trade Log'!O4:O503<>"")*(1)) -> 0 | C5: =SUMPRODUCT((MONTH('📋 Trade Log'!B4:B503)=2)*('📋 Trade Log'!O4:O503="Win")) -> 0 | D5: =SUMPRODUCT((MONTH('📋 Trade Log'!B4:B503)=2)*('📋 Trade Log'!O4:O503="Loss")) -> 0 | E5: =IFERROR(C5/B5,0) -> 0 | F5: =IFERROR(SUMPRODUCT((ISNUMBER('📋 Trade Log'!B4:B503))*(MONTH('📋 Trade Log'!B4:B503)=2)*IF(ISNUMBER('📋 Trade Log'!L4:L503),'📋 Trade Log'!L4:L503,0)),0) -> 0 | G5: =IFERROR(F5/B5,0) -> 0 | H5: =SUM($F$4:F5) -> 0
A6: March | B6: =SUMPRODUCT((ISNUMBER('📋 Trade Log'!B4:B503))*(MONTH('📋 Trade Log'!B4:B503)=3)*('📋 Trade Log'!O4:O503<>"")*(1)) -> 0 | C6: =SUMPRODUCT((MONTH('📋 Trade Log'!B4:B503)=3)*('📋 Trade Log'!O4:O503="Win")) -> 0 | D6: =SUMPRODUCT((MONTH('📋 Trade Log'!B4:B503)=3)*('📋 Trade Log'!O4:O503="Loss")) -> 0 | E6: =IFERROR(C6/B6,0) -> 0 | F6: =IFERROR(SUMPRODUCT((ISNUMBER('📋 Trade Log'!B4:B503))*(MONTH('📋 Trade Log'!B4:B503)=3)*IF(ISNUMBER('📋 Trade Log'!L4:L503),'📋 Trade Log'!L4:L503,0)),0) -> 0 | G6: =IFERROR(F6/B6,0) -> 0 | H6: =SUM($F$4:F6) -> 0
A7: April | B7: =SUMPRODUCT((ISNUMBER('📋 Trade Log'!B4:B503))*(MONTH('📋 Trade Log'!B4:B503)=4)*('📋 Trade Log'!O4:O503<>"")*(1)) -> 0 | C7: =SUMPRODUCT((MONTH('📋 Trade Log'!B4:B503)=4)*('📋 Trade Log'!O4:O503="Win")) -> 0 | D7: =SUMPRODUCT((MONTH('📋 Trade Log'!B4:B503)=4)*('📋 Trade Log'!O4:O503="Loss")) -> 0 | E7: =IFERROR(C7/B7,0) -> 0 | F7: =IFERROR(SUMPRODUCT((ISNUMBER('📋 Trade Log'!B4:B503))*(MONTH('📋 Trade Log'!B4:B503)=4)*IF(ISNUMBER('📋 Trade Log'!L4:L503),'📋 Trade Log'!L4:L503,0)),0) -> 0 | G7: =IFERROR(F7/B7,0) -> 0 | H7: =SUM($F$4:F7) -> 0
A8: May | B8: =SUMPRODUCT((ISNUMBER('📋 Trade Log'!B4:B503))*(MONTH('📋 Trade Log'!B4:B503)=5)*('📋 Trade Log'!O4:O503<>"")*(1)) -> 0 | C8: =SUMPRODUCT((MONTH('📋 Trade Log'!B4:B503)=5)*('📋 Trade Log'!O4:O503="Win")) -> 0 | D8: =SUMPRODUCT((MONTH('📋 Trade Log'!B4:B503)=5)*('📋 Trade Log'!O4:O503="Loss")) -> 0 | E8: =IFERROR(C8/B8,0) -> 0 | F8: =IFERROR(SUMPRODUCT((ISNUMBER('📋 Trade Log'!B4:B503))*(MONTH('📋 Trade Log'!B4:B503)=5)*IF(ISNUMBER('📋 Trade Log'!L4:L503),'📋 Trade Log'!L4:L503,0)),0) -> 0 | G8: =IFERROR(F8/B8,0) -> 0 | H8: =SUM($F$4:F8) -> 0
A9: June | B9: =SUMPRODUCT((ISNUMBER('📋 Trade Log'!B4:B503))*(MONTH('📋 Trade Log'!B4:B503)=6)*('📋 Trade Log'!O4:O503<>"")*(1)) -> 0 | C9: =SUMPRODUCT((MONTH('📋 Trade Log'!B4:B503)=6)*('📋 Trade Log'!O4:O503="Win")) -> 0 | D9: =SUMPRODUCT((MONTH('📋 Trade Log'!B4:B503)=6)*('📋 Trade Log'!O4:O503="Loss")) -> 0 | E9: =IFERROR(C9/B9,0) -> 0 | F9: =IFERROR(SUMPRODUCT((ISNUMBER('📋 Trade Log'!B4:B503))*(MONTH('📋 Trade Log'!B4:B503)=6)*IF(ISNUMBER('📋 Trade Log'!L4:L503),'📋 Trade Log'!L4:L503,0)),0) -> 0 | G9: =IFERROR(F9/B9,0) -> 0 | H9: =SUM($F$4:F9) -> 0
A10: July | B10: =SUMPRODUCT((ISNUMBER('📋 Trade Log'!B4:B503))*(MONTH('📋 Trade Log'!B4:B503)=7)*('📋 Trade Log'!O4:O503<>"")*(1)) -> 0 | C10: =SUMPRODUCT((MONTH('📋 Trade Log'!B4:B503)=7)*('📋 Trade Log'!O4:O503="Win")) -> 0 | D10: =SUMPRODUCT((MONTH('📋 Trade Log'!B4:B503)=7)*('📋 Trade Log'!O4:O503="Loss")) -> 0 | E10: =IFERROR(C10/B10,0) -> 0 | F10: =IFERROR(SUMPRODUCT((ISNUMBER('📋 Trade Log'!B4:B503))*(MONTH('📋 Trade Log'!B4:B503)=7)*IF(ISNUMBER('📋 Trade Log'!L4:L503),'📋 Trade Log'!L4:L503,0)),0) -> 0 | G10: =IFERROR(F10/B10,0) -> 0 | H10: =SUM($F$4:F10) -> 0
A11: August | B11: =SUMPRODUCT((ISNUMBER('📋 Trade Log'!B4:B503))*(MONTH('📋 Trade Log'!B4:B503)=8)*('📋 Trade Log'!O4:O503<>"")*(1)) -> 0 | C11: =SUMPRODUCT((MONTH('📋 Trade Log'!B4:B503)=8)*('📋 Trade Log'!O4:O503="Win")) -> 0 | D11: =SUMPRODUCT((MONTH('📋 Trade Log'!B4:B503)=8)*('📋 Trade Log'!O4:O503="Loss")) -> 0 | E11: =IFERROR(C11/B11,0) -> 0 | F11: =IFERROR(SUMPRODUCT((ISNUMBER('📋 Trade Log'!B4:B503))*(MONTH('📋 Trade Log'!B4:B503)=8)*IF(ISNUMBER('📋 Trade Log'!L4:L503),'📋 Trade Log'!L4:L503,0)),0) -> 0 | G11: =IFERROR(F11/B11,0) -> 0 | H11: =SUM($F$4:F11) -> 0
A12: September | B12: =SUMPRODUCT((ISNUMBER('📋 Trade Log'!B4:B503))*(MONTH('📋 Trade Log'!B4:B503)=9)*('📋 Trade Log'!O4:O503<>"")*(1)) -> 0 | C12: =SUMPRODUCT((MONTH('📋 Trade Log'!B4:B503)=9)*('📋 Trade Log'!O4:O503="Win")) -> 0 | D12: =SUMPRODUCT((MONTH('📋 Trade Log'!B4:B503)=9)*('📋 Trade Log'!O4:O503="Loss")) -> 0 | E12: =IFERROR(C12/B12,0) -> 0 | F12: =IFERROR(SUMPRODUCT((ISNUMBER('📋 Trade Log'!B4:B503))*(MONTH('📋 Trade Log'!B4:B503)=9)*IF(ISNUMBER('📋 Trade Log'!L4:L503),'📋 Trade Log'!L4:L503,0)),0) -> 0 | G12: =IFERROR(F12/B12,0) -> 0 | H12: =SUM($F$4:F12) -> 0
A13: October | B13: =SUMPRODUCT((ISNUMBER('📋 Trade Log'!B4:B503))*(MONTH('📋 Trade Log'!B4:B503)=10)*('📋 Trade Log'!O4:O503<>"")*(1)) -> 0 | C13: =SUMPRODUCT((MONTH('📋 Trade Log'!B4:B503)=10)*('📋 Trade Log'!O4:O503="Win")) -> 0 | D13: =SUMPRODUCT((MONTH('📋 Trade Log'!B4:B503)=10)*('📋 Trade Log'!O4:O503="Loss")) -> 0 | E13: =IFERROR(C13/B13,0) -> 0 | F13: =IFERROR(SUMPRODUCT((ISNUMBER('📋 Trade Log'!B4:B503))*(MONTH('📋 Trade Log'!B4:B503)=10)*IF(ISNUMBER('📋 Trade Log'!L4:L503),'📋 Trade Log'!L4:L503,0)),0) -> 0 | G13: =IFERROR(F13/B13,0) -> 0 | H13: =SUM($F$4:F13) -> 0
A14: November | B14: =SUMPRODUCT((ISNUMBER('📋 Trade Log'!B4:B503))*(MONTH('📋 Trade Log'!B4:B503)=11)*('📋 Trade Log'!O4:O503<>"")*(1)) -> 0 | C14: =SUMPRODUCT((MONTH('📋 Trade Log'!B4:B503)=11)*('📋 Trade Log'!O4:O503="Win")) -> 0 | D14: =SUMPRODUCT((MONTH('📋 Trade Log'!B4:B503)=11)*('📋 Trade Log'!O4:O503="Loss")) -> 0 | E14: =IFERROR(C14/B14,0) -> 0 | F14: =IFERROR(SUMPRODUCT((ISNUMBER('📋 Trade Log'!B4:B503))*(MONTH('📋 Trade Log'!B4:B503)=11)*IF(ISNUMBER('📋 Trade Log'!L4:L503),'📋 Trade Log'!L4:L503,0)),0) -> 0 | G14: =IFERROR(F14/B14,0) -> 0 | H14: =SUM($F$4:F14) -> 0
A15: December | B15: =SUMPRODUCT((ISNUMBER('📋 Trade Log'!B4:B503))*(MONTH('📋 Trade Log'!B4:B503)=12)*('📋 Trade Log'!O4:O503<>"")*(1)) -> 0 | C15: =SUMPRODUCT((MONTH('📋 Trade Log'!B4:B503)=12)*('📋 Trade Log'!O4:O503="Win")) -> 0 | D15: =SUMPRODUCT((MONTH('📋 Trade Log'!B4:B503)=12)*('📋 Trade Log'!O4:O503="Loss")) -> 0 | E15: =IFERROR(C15/B15,0) -> 0 | F15: =IFERROR(SUMPRODUCT((ISNUMBER('📋 Trade Log'!B4:B503))*(MONTH('📋 Trade Log'!B4:B503)=12)*IF(ISNUMBER('📋 Trade Log'!L4:L503),'📋 Trade Log'!L4:L503,0)),0) -> 0 | G15: =IFERROR(F15/B15,0) -> 0 | H15: =SUM($F$4:F15) -> 0
A16: TOTAL | B16: =SUM(B4:B15) -> 0 | C16: =SUM(C4:C15) -> 0 | D16: =SUM(D4:D15) -> 0 | E16: =IFERROR(C16/B16,0) -> 0 | F16: =SUM(F4:F15) -> 0 | G16: =IFERROR(F16/B16,0) -> 0

Sheet 📉 Drawdown & Equity
A1: 📉 EQUITY CURVE & DRAWDOWN TRACKER
A2: ⚙️ Enter your starting capital in cell B3 — everything updates automatically
A3: Starting Capital ($) | B3: 10000
A5: Trade # | B5: Date | C5: P/L ($) | D5: Cum. P/L ($) | E5: Capital ($) | F5: Drawdown ($) | G5: DD %
A6: =IF('📋 Trade Log'!B4<>"",'📋 Trade Log'!A4,"") | B6: =IF('📋 Trade Log'!B4<>"",'📋 Trade Log'!B4,"") | C6: =IF('📋 Trade Log'!L4<>"",'📋 Trade Log'!L4,"") | D6: =IF(A6<>"",SUM($C$6:C6),"") | E6: =IF(A6<>"",B$3+D6,"") | F6: =IF(A6<>"",MIN(0,E6-MAX($E$6:E6)),"") | G6: =IF(A6<>"",IFERROR(F6/MAX($E$6:E6),0),"")
A7: =IF('📋 Trade Log'!B5<>"",'📋 Trade Log'!A5,"") | B7: =IF('📋 Trade Log'!B5<>"",'📋 Trade Log'!B5,"") | C7: =IF('📋 Trade Log'!L5<>"",'📋 Trade Log'!L5,"") | D7: =IF(A7<>"",SUM($C$6:C7),"") | E7: =IF(A7<>"",B$3+D7,"") | F7: =IF(A7<>"",MIN(0,E7-MAX($E$6:E7)),"") | G7: =IF(A7<>"",IFERROR(F7/MAX($E$6:E7),0),"")
A8: =IF('📋 Trade Log'!B6<>"",'📋 Trade Log'!A6,"") | B8: =IF('📋 Trade Log'!B6<>"",'📋 Trade Log'!B6,"") | C8: =IF('📋 Trade Log'!L6<>"",'📋 Trade Log'!L6,"") | D8: =IF(A8<>"",SUM($C$6:C8),"") | E8: =IF(A8<>"",B$3+D8,"") | F8: =IF(A8<>"",MIN(0,E8-MAX($E$6:E8)),"") | G8: =IF(A8<>"",IFERROR(F8/MAX($E$6:E8),0),"")
A9: =IF('📋 Trade Log'!B7<>"",'📋 Trade Log'!A7,"") | B9: =IF('📋 Trade Log'!B7<>"",'📋 Trade Log'!B7,"") | C9: =IF('📋 Trade Log'!L7<>"",'📋 Trade Log'!L7,"") | D9: =IF(A9<>"",SUM($C$6:C9),"") | E9: =IF(A9<>"",B$3+D9,"") | F9: =IF(A9<>"",MIN(0,E9-MAX($E$6:E9)),"") | G9: =IF(A9<>"",IFERROR(F9/MAX($E$6:E9),0),"")
A10: =IF('📋 Trade Log'!B8<>"",'📋 Trade Log'!A8,"") | B10: =IF('📋 Trade Log'!B8<>"",'📋 Trade Log'!B8,"") | C10: =IF('📋 Trade Log'!L8<>"",'📋 Trade Log'!L8,"") | D10: =IF(A10<>"",SUM($C$6:C10),"") | E10: =IF(A10<>"",B$3+D10,"") | F10: =IF(A10<>"",MIN(0,E10-MAX($E$6:E10)),"") | G10: =IF(A10<>"",IFERROR(F10/MAX($E$6:E10),0),"")
A11: =IF('📋 Trade Log'!B9<>"",'📋 Trade Log'!A9,"") | B11: =IF('📋 Trade Log'!B9<>"",'📋 Trade Log'!B9,"") | C11: =IF('📋 Trade Log'!L9<>"",'📋 Trade Log'!L9,"") | D11: =IF(A11<>"",SUM($C$6:C11),"") | E11: =IF(A11<>"",B$3+D11,"") | F11: =IF(A11<>"",MIN(0,E11-MAX($E$6:E11)),"") | G11: =IF(A11<>"",IFERROR(F11/MAX($E$6:E11),0),"")
A12: =IF('📋 Trade Log'!B10<>"",'📋 Trade Log'!A10,"") | B12: =IF('📋 Trade Log'!B10<>"",'📋 Trade Log'!B10,"") | C12: =IF('📋 Trade Log'!L10<>"",'📋 Trade Log'!L10,"") | D12: =IF(A12<>"",SUM($C$6:C12),"") | E12: =IF(A12<>"",B$3+D12,"") | F12: =IF(A12<>"",MIN(0,E12-MAX($E$6:E12)),"") | G12: =IF(A12<>"",IFERROR(F12/MAX($E$6:E12),0),"")
A13: =IF('📋 Trade Log'!B11<>"",'📋 Trade Log'!A11,"") | B13: =IF('📋 Trade Log'!B11<>"",'📋 Trade Log'!B11,"") | C13: =IF('📋 Trade Log'!L11<>"",'📋 Trade Log'!L11,"") | D13: =IF(A13<>"",SUM($C$6:C13),"") | E13: =IF(A13<>"",B$3+D13,"") | F13: =IF(A13<>"",MIN(0,E13-MAX($E$6:E13)),"") | G13: =IF(A13<>"",IFERROR(F13/MAX($E$6:E13),0),"")
A14: =IF('📋 Trade Log'!B12<>"",'📋 Trade Log'!A12,"") | B14: =IF('📋 Trade Log'!B12<>"",'📋 Trade Log'!B12,"") | C14: =IF('📋 Trade Log'!L12<>"",'📋 Trade Log'!L12,"") | D14: =IF(A14<>"",SUM($C$6:C14),"") | E14: =IF(A14<>"",B$3+D14,"") | F14: =IF(A14<>"",MIN(0,E14-MAX($E$6:E14)),"") | G14: =IF(A14<>"",IFERROR(F14/MAX($E$6:E14),0),"")
A15: =IF('📋 Trade Log'!B13<>"",'📋 Trade Log'!A13,"") | B15: =IF('📋 Trade Log'!B13<>"",'📋 Trade Log'!B13,"") | C15: =IF('📋 Trade Log'!L13<>"",'📋 Trade Log'!L13,"") | D15: =IF(A15<>"",SUM($C$6:C15),"") | E15: =IF(A15<>"",B$3+D15,"") | F15: =IF(A15<>"",MIN(0,E15-MAX($E$6:E15)),"") | G15: =IF(A15<>"",IFERROR(F15/MAX($E$6:E15),0),"")
A16: =IF('📋 Trade Log'!B14<>"",'📋 Trade Log'!A14,"") | B16: =IF('📋 Trade Log'!B14<>"",'📋 Trade Log'!B14,"") | C16: =IF('📋 Trade Log'!L14<>"",'📋 Trade Log'!L14,"") | D16: =IF(A16<>"",SUM($C$6:C16),"") | E16: =IF(A16<>"",B$3+D16,"") | F16: =IF(A16<>"",MIN(0,E16-MAX($E$6:E16)),"") | G16: =IF(A16<>"",IFERROR(F16/MAX($E$6:E16),0),"")
A17: =IF('📋 Trade Log'!B15<>"",'📋 Trade Log'!A15,"") | B17: =IF('📋 Trade Log'!B15<>"",'📋 Trade Log'!B15,"") | C17: =IF('📋 Trade Log'!L15<>"",'📋 Trade Log'!L15,"") | D17: =IF(A17<>"",SUM($C$6:C17),"") | E17: =IF(A17<>"",B$3+D17,"") | F17: =IF(A17<>"",MIN(0,E17-MAX($E$6:E17)),"") | G17: =IF(A17<>"",IFERROR(F17/MAX($E$6:E17),0),"")
... A505: =IF('📋 Trade Log'!B503<>"",'📋 Trade Log'!A503,"") | B505: =IF('📋 Trade Log'!B503<>"",'📋 Trade Log'!B503,"") | C505: =IF('📋 Trade Log'!L503<>"",'📋 Trade Log'!L503,"") | D505: =IF(A505<>"",SUM($C$6:C505),"") | E505: =IF(A505<>"",B$3+D505,"") | F505: =IF(A505<>"",MIN(0,E505-MAX($E$6:E505)),"") | G505: =IF(A505<>"",IFERROR(F505/MAX($E$6:E505),0),"")

Sheet ℹ️ Guide
A1: ℹ️ HOW TO USE – NQ TRADING JOURNAL
A3: 📋 Trade Log – Required Fields
A4: Date | B4: Trade date (MM/DD/YYYY)
A5: Session | B5: Asia / London / NY Open / New York
A6: Direction | B6: Long or Short (exactly as shown)
A7: Entry | B7: Entry price in points (e.g. 21250.50)
A8: Stop Loss | B8: Stop loss price in points
A9: Take Profit | B9: Target price in points
A10: Exit | B10: Actual exit price
A11: Contracts | B11: Number of contracts traded
A12: Setup | B12: Your setup name (e.g. ICT, Breakout, VWAP)
A14: 📊 Auto-Calculated – Do NOT type these!
A15: Weekday | B15: Derived from Date automatically
A16: Points P/L | B16: (Exit – Entry) × 20 (NQ multiplier)
A17: $ P/L | B17: Points × Contracts
A18: R:R Plan | B18: (TP – Entry) / (Entry – SL)
A19: R:R Actual | B19: (Exit – Entry) / (Entry – SL)
A20: Win/Loss | B20: Auto: Win / Loss / Break Even
A22: 💡 Key Facts
A23: NQ Point Value | B23: 1 point NQ = $20 per contract
A24: Session Times | B24: Asia 01-08h, London 08-14h, NY Open 14-16h, NY 16-21h (UTC)
A25: Mistake? Column | B25: Y (Yes) / N (No) – for personal mistake analysis
A26: Starting Capital | B26: Sheet 'Drawdown & Equity' → Cell B3
